[
    {
        "id": 14987,
        "name": "Atta Abad",
        "name_l1": "عطا آباد",
        "externalID": "16502",
        "slug": "/Hunza_Atta_Abad-16502",
        "slug_l1": "/Hunza_Atta_Abad-16502",
        "_geoloc": {
            "lat": 36.313884,
            "lng": 74.808328
        },
        "geography": {
            "lat": 36.313884,
            "lng": 74.808328
        },
        "geo_point": [
            74.808328,
            36.313884
        ],
        "level": 3,
        "hierarchy": [
            {
                "id": 2,
                "level": 0,
                "externalID": "1521",
                "name": "Pakistan",
                "name_l1": "پاکستان",
                "slug": "/Pakistan-1521",
                "slug_l1": "/Pakistan-1521"
            },
            {
                "id": 8,
                "level": 1,
                "externalID": "1526",
                "name": "Gilgit Baltistan",
                "name_l1": "گلگت بلتستان",
                "slug": "/Gilgit_Baltistan-1526",
                "slug_l1": "/Gilgit_Baltistan-1526"
            },
            {
                "id": 79,
                "level": 2,
                "externalID": "1546",
                "name": "Hunza",
                "name_l1": "ہنزہ",
                "slug": "/Hunza-1546",
                "slug_l1": "/Hunza-1546"
            },
            {
                "id": 14987,
                "level": 3,
                "externalID": "16502",
                "name": "Atta Abad",
                "name_l1": "عطا آباد",
                "slug": "/Hunza_Atta_Abad-16502",
                "slug_l1": "/Hunza_Atta_Abad-16502"
            }
        ],
        "hierarchyPath": "Atta Abad Hunza Gilgit Baltistan Pakistan",
        "adCount": 6,
        "aliases": [],
        "type": null,
        "hasBuilding": false,
        "trackID": "16502",
        "roles": null,
        "completionStatus": null,
        "hasChildren": false,
        "polygon": null,
        "objectID": "14987",
        "_highlightResult": {
            "name": {
                "value": "Atta Abad",
                "matchLevel": "none",
                "matchedWords": []
            }
        }
    },
    {
        "id": 79,
        "name": "Hunza",
        "name_l1": "ہنزہ",
        "externalID": "1546",
        "slug": "/Hunza-1546",
        "slug_l1": "/Hunza-1546",
        "_geoloc": {
            "lat": 36.316434,
            "lng": 74.649989
        },
        "geography": {
            "lat": 36.316434,
            "lng": 74.649989
        },
        "geo_point": [
            74.649989,
            36.316434
        ],
        "level": 2,
        "hierarchy": [
            {
                "id": 2,
                "level": 0,
                "externalID": "1521",
                "name": "Pakistan",
                "name_l1": "پاکستان",
                "slug": "/Pakistan-1521",
                "slug_l1": "/Pakistan-1521"
            },
            {
                "id": 8,
                "level": 1,
                "externalID": "1526",
                "name": "Gilgit Baltistan",
                "name_l1": "گلگت بلتستان",
                "slug": "/Gilgit_Baltistan-1526",
                "slug_l1": "/Gilgit_Baltistan-1526"
            },
            {
                "id": 79,
                "level": 2,
                "externalID": "1546",
                "name": "Hunza",
                "name_l1": "ہنزہ",
                "slug": "/Hunza-1546",
                "slug_l1": "/Hunza-1546"
            }
        ],
        "hierarchyPath": "Hunza Gilgit Baltistan Pakistan",
        "adCount": 6,
        "aliases": [],
        "type": null,
        "hasBuilding": false,
        "trackID": "1546",
        "roles": null,
        "completionStatus": null,
        "hasChildren": true,
        "polygon": null,
        "objectID": "79",
        "_highlightResult": {
            "name": {
                "value": "Hunza",
                "matchLevel": "none",
                "matchedWords": []
            }
        }
    },
    {
        "id": 3914,
        "name": "Ahmad Abad",
        "name_l1": "احمد آباد",
        "externalID": "8055",
        "slug": "/Hunza_Ahmad_Abad-8055",
        "slug_l1": "/Hunza_Ahmad_Abad-8055",
        "_geoloc": {
            "lat": 36.305995,
            "lng": 74.733067
        },
        "geography": {
            "lat": 36.305995,
            "lng": 74.733067
        },
        "geo_point": [
            74.733067,
            36.305995
        ],
        "level": 3,
        "hierarchy": [
            {
                "id": 2,
                "level": 0,
                "externalID": "1521",
                "name": "Pakistan",
                "name_l1": "پاکستان",
                "slug": "/Pakistan-1521",
                "slug_l1": "/Pakistan-1521"
            },
            {
                "id": 8,
                "level": 1,
                "externalID": "1526",
                "name": "Gilgit Baltistan",
                "name_l1": "گلگت بلتستان",
                "slug": "/Gilgit_Baltistan-1526",
                "slug_l1": "/Gilgit_Baltistan-1526"
            },
            {
                "id": 79,
                "level": 2,
                "externalID": "1546",
                "name": "Hunza",
                "name_l1": "ہنزہ",
                "slug": "/Hunza-1546",
                "slug_l1": "/Hunza-1546"
            },
            {
                "id": 3914,
                "level": 3,
                "externalID": "8055",
                "name": "Ahmad Abad",
                "name_l1": "احمد آباد",
                "slug": "/Hunza_Ahmad_Abad-8055",
                "slug_l1": "/Hunza_Ahmad_Abad-8055"
            }
        ],
        "hierarchyPath": "Ahmad Abad Hunza Gilgit Baltistan Pakistan",
        "adCount": 0,
        "aliases": [],
        "type": null,
        "hasBuilding": false,
        "trackID": "8055",
        "roles": null,
        "completionStatus": null,
        "hasChildren": false,
        "polygon": null,
        "objectID": "3914",
        "_highlightResult": {
            "name": {
                "value": "Ahmad Abad",
                "matchLevel": "none",
                "matchedWords": []
            }
        }
    },
    {
        "id": 3915,
        "name": "Ali Abad",
        "name_l1": "علی آباد",
        "externalID": "8056",
        "slug": "/Hunza_Ali_Abad-8056",
        "slug_l1": "/Hunza_Ali_Abad-8056",
        "_geoloc": {
            "lat": 36.309592,
            "lng": 74.614906
        },
        "geography": {
            "lat": 36.309592,
            "lng": 74.614906
        },
        "geo_point": [
            74.614906,
            36.309592
        ],
        "level": 3,
        "hierarchy": [
            {
                "id": 2,
                "level": 0,
                "externalID": "1521",
                "name": "Pakistan",
                "name_l1": "پاکستان",
                "slug": "/Pakistan-1521",
                "slug_l1": "/Pakistan-1521"
            },
            {
                "id": 8,
                "level": 1,
                "externalID": "1526",
                "name": "Gilgit Baltistan",
                "name_l1": "گلگت بلتستان",
                "slug": "/Gilgit_Baltistan-1526",
                "slug_l1": "/Gilgit_Baltistan-1526"
            },
            {
                "id": 79,
                "level": 2,
                "externalID": "1546",
                "name": "Hunza",
                "name_l1": "ہنزہ",
                "slug": "/Hunza-1546",
                "slug_l1": "/Hunza-1546"
            },
            {
                "id": 3915,
                "level": 3,
                "externalID": "8056",
                "name": "Ali Abad",
                "name_l1": "علی آباد",
                "slug": "/Hunza_Ali_Abad-8056",
                "slug_l1": "/Hunza_Ali_Abad-8056"
            }
        ],
        "hierarchyPath": "Ali Abad Hunza Gilgit Baltistan Pakistan",
        "adCount": 0,
        "aliases": [],
        "type": null,
        "hasBuilding": false,
        "trackID": "8056",
        "roles": null,
        "completionStatus": null,
        "hasChildren": true,
        "polygon": null,
        "objectID": "3915",
        "_highlightResult": {
            "name": {
                "value": "Ali Abad",
                "matchLevel": "none",
                "matchedWords": []
            }
        }
    },
    {
        "id": 21246,
        "name": "Ambiance Resort Hunza",
        "name_l1": "ایمبیئنس ریزورٹ ہنزہ",
        "externalID": "21836",
        "slug": "/Hunza_Ali_Abad_Ambiance_Resort_Hunza-21836",
        "slug_l1": "/Hunza_Ali_Abad_Ambiance_Resort_Hunza-21836",
        "_geoloc": {
            "lat": 36.302578477566,
            "lng": 74.604994089671
        },
        "geography": {
            "lat": 36.302578477566,
            "lng": 74.604994089671
        },
        "geo_point": [
            74.604994089671,
            36.302578477566
        ],
        "level": 4,
        "hierarchy": [
            {
                "id": 2,
                "level": 0,
                "externalID": "1521",
                "name": "Pakistan",
                "name_l1": "پاکستان",
                "slug": "/Pakistan-1521",
                "slug_l1": "/Pakistan-1521"
            },
            {
                "id": 8,
                "level": 1,
                "externalID": "1526",
                "name": "Gilgit Baltistan",
                "name_l1": "گلگت بلتستان",
                "slug": "/Gilgit_Baltistan-1526",
                "slug_l1": "/Gilgit_Baltistan-1526"
            },
            {
                "id": 79,
                "level": 2,
                "externalID": "1546",
                "name": "Hunza",
                "name_l1": "ہنزہ",
                "slug": "/Hunza-1546",
                "slug_l1": "/Hunza-1546"
            },
            {
                "id": 3915,
                "level": 3,
                "externalID": "8056",
                "name": "Ali Abad",
                "name_l1": "علی آباد",
                "slug": "/Hunza_Ali_Abad-8056",
                "slug_l1": "/Hunza_Ali_Abad-8056"
            },
            {
                "id": 21246,
                "level": 4,
                "externalID": "21836",
                "name": "Ambiance Resort Hunza",
                "name_l1": "ایمبیئنس ریزورٹ ہنزہ",
                "slug": "/Hunza_Ali_Abad_Ambiance_Resort_Hunza-21836",
                "slug_l1": "/Hunza_Ali_Abad_Ambiance_Resort_Hunza-21836"
            }
        ],
        "hierarchyPath": "Ambiance Resort Hunza Ali Abad Hunza Gilgit Baltistan Pakistan",
        "adCount": 0,
        "aliases": [],
        "type": null,
        "hasBuilding": false,
        "trackID": "21836",
        "roles": null,
        "completionStatus": null,
        "hasChildren": false,
        "polygon": null,
        "objectID": "21246",
        "_highlightResult": {
            "name": {
                "value": "Ambiance Resort Hunza",
                "matchLevel": "none",
                "matchedWords": []
            }
        }
    },
    {
        "id": 3916,
        "name": "Bar Budalas Road",
        "name_l1": "بار بودالس روڈ",
        "externalID": "8057",
        "slug": "/Hunza_Bar_Budalas_Road-8057",
        "slug_l1": "/Hunza_Bar_Budalas_Road-8057",
        "_geoloc": {
            "lat": 36.275694,
            "lng": 74.333582
        },
        "geography": {
            "lat": 36.275694,
            "lng": 74.333582
        },
        "geo_point": [
            74.333582,
            36.275694
        ],
        "level": 3,
        "hierarchy": [
            {
                "id": 2,
                "level": 0,
                "externalID": "1521",
                "name": "Pakistan",
                "name_l1": "پاکستان",
                "slug": "/Pakistan-1521",
                "slug_l1": "/Pakistan-1521"
            },
            {
                "id": 8,
                "level": 1,
                "externalID": "1526",
                "name": "Gilgit Baltistan",
                "name_l1": "گلگت بلتستان",
                "slug": "/Gilgit_Baltistan-1526",
                "slug_l1": "/Gilgit_Baltistan-1526"
            },
            {
                "id": 79,
                "level": 2,
                "externalID": "1546",
                "name": "Hunza",
                "name_l1": "ہنزہ",
                "slug": "/Hunza-1546",
                "slug_l1": "/Hunza-1546"
            },
            {
                "id": 3916,
                "level": 3,
                "externalID": "8057",
                "name": "Bar Budalas Road",
                "name_l1": "بار بودالس روڈ",
                "slug": "/Hunza_Bar_Budalas_Road-8057",
                "slug_l1": "/Hunza_Bar_Budalas_Road-8057"
            }
        ],
        "hierarchyPath": "Bar Budalas Road Hunza Gilgit Baltistan Pakistan",
        "adCount": 0,
        "aliases": [],
        "type": null,
        "hasBuilding": false,
        "trackID": "8057",
        "roles": null,
        "completionStatus": null,
        "hasChildren": false,
        "polygon": null,
        "objectID": "3916",
        "_highlightResult": {
            "name": {
                "value": "Bar Budalas Road",
                "matchLevel": "none",
                "matchedWords": []
            }
        }
    },
    {
        "id": 3917,
        "name": "Bar Das Chalt Nagar",
        "name_l1": "بار دس چلت نگر",
        "externalID": "8058",
        "slug": "/Hunza_Bar_Das_Chalt_Nagar-8058",
        "slug_l1": "/Hunza_Bar_Das_Chalt_Nagar-8058",
        "_geoloc": {
            "lat": 36.332828,
            "lng": 74.285431
        },
        "geography": {
            "lat": 36.332828,
            "lng": 74.285431
        },
        "geo_point": [
            74.285431,
            36.332828
        ],
        "level": 3,
        "hierarchy": [
            {
                "id": 2,
                "level": 0,
                "externalID": "1521",
                "name": "Pakistan",
                "name_l1": "پاکستان",
                "slug": "/Pakistan-1521",
                "slug_l1": "/Pakistan-1521"
            },
            {
                "id": 8,
                "level": 1,
                "externalID": "1526",
                "name": "Gilgit Baltistan",
                "name_l1": "گلگت بلتستان",
                "slug": "/Gilgit_Baltistan-1526",
                "slug_l1": "/Gilgit_Baltistan-1526"
            },
            {
                "id": 79,
                "level": 2,
                "externalID": "1546",
                "name": "Hunza",
                "name_l1": "ہنزہ",
                "slug": "/Hunza-1546",
                "slug_l1": "/Hunza-1546"
            },
            {
                "id": 3917,
                "level": 3,
                "externalID": "8058",
                "name": "Bar Das Chalt Nagar",
                "name_l1": "بار دس چلت نگر",
                "slug": "/Hunza_Bar_Das_Chalt_Nagar-8058",
                "slug_l1": "/Hunza_Bar_Das_Chalt_Nagar-8058"
            }
        ],
        "hierarchyPath": "Bar Das Chalt Nagar Hunza Gilgit Baltistan Pakistan",
        "adCount": 0,
        "aliases": [],
        "type": null,
        "hasBuilding": false,
        "trackID": "8058",
        "roles": null,
        "completionStatus": null,
        "hasChildren": false,
        "polygon": null,
        "objectID": "3917",
        "_highlightResult": {
            "name": {
                "value": "Bar Das Chalt Nagar",
                "matchLevel": "none",
                "matchedWords": []
            }
        }
    },
    {
        "id": 3918,
        "name": "Bar Khass Chalt Nagar",
        "name_l1": "بار خاص چلت نگر",
        "externalID": "8059",
        "slug": "/Hunza_Bar_Khass_Chalt_Nagar-8059",
        "slug_l1": "/Hunza_Bar_Khass_Chalt_Nagar-8059",
        "_geoloc": {
            "lat": 36.384807,
            "lng": 74.281082
        },
        "geography": {
            "lat": 36.384807,
            "lng": 74.281082
        },
        "geo_point": [
            74.281082,
            36.384807
        ],
        "level": 3,
        "hierarchy": [
            {
                "id": 2,
                "level": 0,
                "externalID": "1521",
                "name": "Pakistan",
                "name_l1": "پاکستان",
                "slug": "/Pakistan-1521",
                "slug_l1": "/Pakistan-1521"
            },
            {
                "id": 8,
                "level": 1,
                "externalID": "1526",
                "name": "Gilgit Baltistan",
                "name_l1": "گلگت بلتستان",
                "slug": "/Gilgit_Baltistan-1526",
                "slug_l1": "/Gilgit_Baltistan-1526"
            },
            {
                "id": 79,
                "level": 2,
                "externalID": "1546",
                "name": "Hunza",
                "name_l1": "ہنزہ",
                "slug": "/Hunza-1546",
                "slug_l1": "/Hunza-1546"
            },
            {
                "id": 3918,
                "level": 3,
                "externalID": "8059",
                "name": "Bar Khass Chalt Nagar",
                "name_l1": "بار خاص چلت نگر",
                "slug": "/Hunza_Bar_Khass_Chalt_Nagar-8059",
                "slug_l1": "/Hunza_Bar_Khass_Chalt_Nagar-8059"
            }
        ],
        "hierarchyPath": "Bar Khass Chalt Nagar Hunza Gilgit Baltistan Pakistan",
        "adCount": 0,
        "aliases": [],
        "type": null,
        "hasBuilding": false,
        "trackID": "8059",
        "roles": null,
        "completionStatus": null,
        "hasChildren": false,
        "polygon": null,
        "objectID": "3918",
        "_highlightResult": {
            "name": {
                "value": "Bar Khass Chalt Nagar",
                "matchLevel": "none",
                "matchedWords": []
            }
        }
    },
    {
        "id": 3919,
        "name": "Bharpoo Hopar Nagar",
        "name_l1": "بھارپو ہوپر نگر",
        "externalID": "8060",
        "slug": "/Hunza_Bharpoo_Hopar_Nagar-8060",
        "slug_l1": "/Hunza_Bharpoo_Hopar_Nagar-8060",
        "_geoloc": {
            "lat": 36.152846,
            "lng": 74.873085
        },
        "geography": {
            "lat": 36.152846,
            "lng": 74.873085
        },
        "geo_point": [
            74.873085,
            36.152846
        ],
        "level": 3,
        "hierarchy": [
            {
                "id": 2,
                "level": 0,
                "externalID": "1521",
                "name": "Pakistan",
                "name_l1": "پاکستان",
                "slug": "/Pakistan-1521",
                "slug_l1": "/Pakistan-1521"
            },
            {
                "id": 8,
                "level": 1,
                "externalID": "1526",
                "name": "Gilgit Baltistan",
                "name_l1": "گلگت بلتستان",
                "slug": "/Gilgit_Baltistan-1526",
                "slug_l1": "/Gilgit_Baltistan-1526"
            },
            {
                "id": 79,
                "level": 2,
                "externalID": "1546",
                "name": "Hunza",
                "name_l1": "ہنزہ",
                "slug": "/Hunza-1546",
                "slug_l1": "/Hunza-1546"
            },
            {
                "id": 3919,
                "level": 3,
                "externalID": "8060",
                "name": "Bharpoo Hopar Nagar",
                "name_l1": "بھارپو ہوپر نگر",
                "slug": "/Hunza_Bharpoo_Hopar_Nagar-8060",
                "slug_l1": "/Hunza_Bharpoo_Hopar_Nagar-8060"
            }
        ],
        "hierarchyPath": "Bharpoo Hopar Nagar Hunza Gilgit Baltistan Pakistan",
        "adCount": 0,
        "aliases": [],
        "type": null,
        "hasBuilding": false,
        "trackID": "8060",
        "roles": null,
        "completionStatus": null,
        "hasChildren": false,
        "polygon": null,
        "objectID": "3919",
        "_highlightResult": {
            "name": {
                "value": "Bharpoo Hopar Nagar",
                "matchLevel": "none",
                "matchedWords": []
            }
        }
    },
    {
        "id": 3920,
        "name": "Bharpoo Road",
        "name_l1": "بھارپو روڈ",
        "externalID": "8061",
        "slug": "/Hunza_Bharpoo_Road-8061",
        "slug_l1": "/Hunza_Bharpoo_Road-8061",
        "_geoloc": {
            "lat": 36.193863,
            "lng": 74.836121
        },
        "geography": {
            "lat": 36.193863,
            "lng": 74.836121
        },
        "geo_point": [
            74.836121,
            36.193863
        ],
        "level": 3,
        "hierarchy": [
            {
                "id": 2,
                "level": 0,
                "externalID": "1521",
                "name": "Pakistan",
                "name_l1": "پاکستان",
                "slug": "/Pakistan-1521",
                "slug_l1": "/Pakistan-1521"
            },
            {
                "id": 8,
                "level": 1,
                "externalID": "1526",
                "name": "Gilgit Baltistan",
                "name_l1": "گلگت بلتستان",
                "slug": "/Gilgit_Baltistan-1526",
                "slug_l1": "/Gilgit_Baltistan-1526"
            },
            {
                "id": 79,
                "level": 2,
                "externalID": "1546",
                "name": "Hunza",
                "name_l1": "ہنزہ",
                "slug": "/Hunza-1546",
                "slug_l1": "/Hunza-1546"
            },
            {
                "id": 3920,
                "level": 3,
                "externalID": "8061",
                "name": "Bharpoo Road",
                "name_l1": "بھارپو روڈ",
                "slug": "/Hunza_Bharpoo_Road-8061",
                "slug_l1": "/Hunza_Bharpoo_Road-8061"
            }
        ],
        "hierarchyPath": "Bharpoo Road Hunza Gilgit Baltistan Pakistan",
        "adCount": 0,
        "aliases": [],
        "type": null,
        "hasBuilding": false,
        "trackID": "8061",
        "roles": null,
        "completionStatus": null,
        "hasChildren": false,
        "polygon": null,
        "objectID": "3920",
        "_highlightResult": {
            "name": {
                "value": "Bharpoo Road",
                "matchLevel": "none",
                "matchedWords": []
            }
        }
    },
    {
        "id": 3921,
        "name": "Budalas Chalt Nagar",
        "name_l1": "بودالس چلت نگر",
        "externalID": "8062",
        "slug": "/Hunza_Budalas_Chalt_Nagar-8062",
        "slug_l1": "/Hunza_Budalas_Chalt_Nagar-8062",
        "_geoloc": {
            "lat": 36.280814,
            "lng": 74.334869
        },
        "geography": {
            "lat": 36.280814,
            "lng": 74.334869
        },
        "geo_point": [
            74.334869,
            36.280814
        ],
        "level": 3,
        "hierarchy": [
            {
                "id": 2,
                "level": 0,
                "externalID": "1521",
                "name": "Pakistan",
                "name_l1": "پاکستان",
                "slug": "/Pakistan-1521",
                "slug_l1": "/Pakistan-1521"
            },
            {
                "id": 8,
                "level": 1,
                "externalID": "1526",
                "name": "Gilgit Baltistan",
                "name_l1": "گلگت بلتستان",
                "slug": "/Gilgit_Baltistan-1526",
                "slug_l1": "/Gilgit_Baltistan-1526"
            },
            {
                "id": 79,
                "level": 2,
                "externalID": "1546",
                "name": "Hunza",
                "name_l1": "ہنزہ",
                "slug": "/Hunza-1546",
                "slug_l1": "/Hunza-1546"
            },
            {
                "id": 3921,
                "level": 3,
                "externalID": "8062",
                "name": "Budalas Chalt Nagar",
                "name_l1": "بودالس چلت نگر",
                "slug": "/Hunza_Budalas_Chalt_Nagar-8062",
                "slug_l1": "/Hunza_Budalas_Chalt_Nagar-8062"
            }
        ],
        "hierarchyPath": "Budalas Chalt Nagar Hunza Gilgit Baltistan Pakistan",
        "adCount": 0,
        "aliases": [],
        "type": null,
        "hasBuilding": false,
        "trackID": "8062",
        "roles": null,
        "completionStatus": null,
        "hasChildren": false,
        "polygon": null,
        "objectID": "3921",
        "_highlightResult": {
            "name": {
                "value": "Budalas Chalt Nagar",
                "matchLevel": "none",
                "matchedWords": []
            }
        }
    },
    {
        "id": 3922,
        "name": "Bul Das",
        "name_l1": "بُل دس",
        "externalID": "8063",
        "slug": "/Hunza_Bul_Das-8063",
        "slug_l1": "/Hunza_Bul_Das-8063",
        "_geoloc": {
            "lat": 36.314849,
            "lng": 74.646893
        },
        "geography": {
            "lat": 36.314849,
            "lng": 74.646893
        },
        "geo_point": [
            74.646893,
            36.314849
        ],
        "level": 3,
        "hierarchy": [
            {
                "id": 2,
                "level": 0,
                "externalID": "1521",
                "name": "Pakistan",
                "name_l1": "پاکستان",
                "slug": "/Pakistan-1521",
                "slug_l1": "/Pakistan-1521"
            },
            {
                "id": 8,
                "level": 1,
                "externalID": "1526",
                "name": "Gilgit Baltistan",
                "name_l1": "گلگت بلتستان",
                "slug": "/Gilgit_Baltistan-1526",
                "slug_l1": "/Gilgit_Baltistan-1526"
            },
            {
                "id": 79,
                "level": 2,
                "externalID": "1546",
                "name": "Hunza",
                "name_l1": "ہنزہ",
                "slug": "/Hunza-1546",
                "slug_l1": "/Hunza-1546"
            },
            {
                "id": 3922,
                "level": 3,
                "externalID": "8063",
                "name": "Bul Das",
                "name_l1": "بُل دس",
                "slug": "/Hunza_Bul_Das-8063",
                "slug_l1": "/Hunza_Bul_Das-8063"
            }
        ],
        "hierarchyPath": "Bul Das Hunza Gilgit Baltistan Pakistan",
        "adCount": 0,
        "aliases": [],
        "type": null,
        "hasBuilding": false,
        "trackID": "8063",
        "roles": null,
        "completionStatus": null,
        "hasChildren": false,
        "polygon": null,
        "objectID": "3922",
        "_highlightResult": {
            "name": {
                "value": "Bul Das",
                "matchLevel": "none",
                "matchedWords": []
            }
        }
    },
    {
        "id": 3923,
        "name": "Chalt Nagar",
        "name_l1": "چلت نگر",
        "externalID": "8064",
        "slug": "/Hunza_Chalt_Nagar-8064",
        "slug_l1": "/Hunza_Chalt_Nagar-8064",
        "_geoloc": {
            "lat": 36.252026,
            "lng": 74.325256
        },
        "geography": {
            "lat": 36.252026,
            "lng": 74.325256
        },
        "geo_point": [
            74.325256,
            36.252026
        ],
        "level": 3,
        "hierarchy": [
            {
                "id": 2,
                "level": 0,
                "externalID": "1521",
                "name": "Pakistan",
                "name_l1": "پاکستان",
                "slug": "/Pakistan-1521",
                "slug_l1": "/Pakistan-1521"
            },
            {
                "id": 8,
                "level": 1,
                "externalID": "1526",
                "name": "Gilgit Baltistan",
                "name_l1": "گلگت بلتستان",
                "slug": "/Gilgit_Baltistan-1526",
                "slug_l1": "/Gilgit_Baltistan-1526"
            },
            {
                "id": 79,
                "level": 2,
                "externalID": "1546",
                "name": "Hunza",
                "name_l1": "ہنزہ",
                "slug": "/Hunza-1546",
                "slug_l1": "/Hunza-1546"
            },
            {
                "id": 3923,
                "level": 3,
                "externalID": "8064",
                "name": "Chalt Nagar",
                "name_l1": "چلت نگر",
                "slug": "/Hunza_Chalt_Nagar-8064",
                "slug_l1": "/Hunza_Chalt_Nagar-8064"
            }
        ],
        "hierarchyPath": "Chalt Nagar Hunza Gilgit Baltistan Pakistan",
        "adCount": 0,
        "aliases": [],
        "type": null,
        "hasBuilding": false,
        "trackID": "8064",
        "roles": null,
        "completionStatus": null,
        "hasChildren": false,
        "polygon": null,
        "objectID": "3923",
        "_highlightResult": {
            "name": {
                "value": "Chalt Nagar",
                "matchLevel": "none",
                "matchedWords": []
            }
        }
    },
    {
        "id": 3924,
        "name": "Dorkhan",
        "name_l1": "دورخان",
        "externalID": "8065",
        "slug": "/Hunza_Dorkhan-8065",
        "slug_l1": "/Hunza_Dorkhan-8065",
        "_geoloc": {
            "lat": 36.314019,
            "lng": 74.625263
        },
        "geography": {
            "lat": 36.314019,
            "lng": 74.625263
        },
        "geo_point": [
            74.625263,
            36.314019
        ],
        "level": 3,
        "hierarchy": [
            {
                "id": 2,
                "level": 0,
                "externalID": "1521",
                "name": "Pakistan",
                "name_l1": "پاکستان",
                "slug": "/Pakistan-1521",
                "slug_l1": "/Pakistan-1521"
            },
            {
                "id": 8,
                "level": 1,
                "externalID": "1526",
                "name": "Gilgit Baltistan",
                "name_l1": "گلگت بلتستان",
                "slug": "/Gilgit_Baltistan-1526",
                "slug_l1": "/Gilgit_Baltistan-1526"
            },
            {
                "id": 79,
                "level": 2,
                "externalID": "1546",
                "name": "Hunza",
                "name_l1": "ہنزہ",
                "slug": "/Hunza-1546",
                "slug_l1": "/Hunza-1546"
            },
            {
                "id": 3924,
                "level": 3,
                "externalID": "8065",
                "name": "Dorkhan",
                "name_l1": "دورخان",
                "slug": "/Hunza_Dorkhan-8065",
                "slug_l1": "/Hunza_Dorkhan-8065"
            }
        ],
        "hierarchyPath": "Dorkhan Hunza Gilgit Baltistan Pakistan",
        "adCount": 0,
        "aliases": [],
        "type": null,
        "hasBuilding": false,
        "trackID": "8065",
        "roles": null,
        "completionStatus": null,
        "hasChildren": false,
        "polygon": null,
        "objectID": "3924",
        "_highlightResult": {
            "name": {
                "value": "Dorkhan",
                "matchLevel": "none",
                "matchedWords": []
            }
        }
    },
    {
        "id": 3925,
        "name": "Ghasho Shal",
        "name_l1": "غشو شَل",
        "externalID": "8066",
        "slug": "/Hunza_Ghasho_Shal-8066",
        "slug_l1": "/Hunza_Ghasho_Shal-8066",
        "_geoloc": {
            "lat": 36.214917,
            "lng": 74.771519
        },
        "geography": {
            "lat": 36.214917,
            "lng": 74.771519
        },
        "geo_point": [
            74.771519,
            36.214917
        ],
        "level": 3,
        "hierarchy": [
            {
                "id": 2,
                "level": 0,
                "externalID": "1521",
                "name": "Pakistan",
                "name_l1": "پاکستان",
                "slug": "/Pakistan-1521",
                "slug_l1": "/Pakistan-1521"
            },
            {
                "id": 8,
                "level": 1,
                "externalID": "1526",
                "name": "Gilgit Baltistan",
                "name_l1": "گلگت بلتستان",
                "slug": "/Gilgit_Baltistan-1526",
                "slug_l1": "/Gilgit_Baltistan-1526"
            },
            {
                "id": 79,
                "level": 2,
                "externalID": "1546",
                "name": "Hunza",
                "name_l1": "ہنزہ",
                "slug": "/Hunza-1546",
                "slug_l1": "/Hunza-1546"
            },
            {
                "id": 3925,
                "level": 3,
                "externalID": "8066",
                "name": "Ghasho Shal",
                "name_l1": "غشو شَل",
                "slug": "/Hunza_Ghasho_Shal-8066",
                "slug_l1": "/Hunza_Ghasho_Shal-8066"
            }
        ],
        "hierarchyPath": "Ghasho Shal Hunza Gilgit Baltistan Pakistan",
        "adCount": 0,
        "aliases": [],
        "type": null,
        "hasBuilding": false,
        "trackID": "8066",
        "roles": null,
        "completionStatus": null,
        "hasChildren": false,
        "polygon": null,
        "objectID": "3925",
        "_highlightResult": {
            "name": {
                "value": "Ghasho Shal",
                "matchLevel": "none",
                "matchedWords": []
            }
        }
    },
    {
        "id": 3926,
        "name": "Ghulmet Nagar",
        "name_l1": "گھلمت نگر",
        "externalID": "8067",
        "slug": "/Hunza_Ghulmet_Nagar-8067",
        "slug_l1": "/Hunza_Ghulmet_Nagar-8067",
        "_geoloc": {
            "lat": 36.245381,
            "lng": 74.47197
        },
        "geography": {
            "lat": 36.245381,
            "lng": 74.47197
        },
        "geo_point": [
            74.47197,
            36.245381
        ],
        "level": 3,
        "hierarchy": [
            {
                "id": 2,
                "level": 0,
                "externalID": "1521",
                "name": "Pakistan",
                "name_l1": "پاکستان",
                "slug": "/Pakistan-1521",
                "slug_l1": "/Pakistan-1521"
            },
            {
                "id": 8,
                "level": 1,
                "externalID": "1526",
                "name": "Gilgit Baltistan",
                "name_l1": "گلگت بلتستان",
                "slug": "/Gilgit_Baltistan-1526",
                "slug_l1": "/Gilgit_Baltistan-1526"
            },
            {
                "id": 79,
                "level": 2,
                "externalID": "1546",
                "name": "Hunza",
                "name_l1": "ہنزہ",
                "slug": "/Hunza-1546",
                "slug_l1": "/Hunza-1546"
            },
            {
                "id": 3926,
                "level": 3,
                "externalID": "8067",
                "name": "Ghulmet Nagar",
                "name_l1": "گھلمت نگر",
                "slug": "/Hunza_Ghulmet_Nagar-8067",
                "slug_l1": "/Hunza_Ghulmet_Nagar-8067"
            }
        ],
        "hierarchyPath": "Ghulmet Nagar Hunza Gilgit Baltistan Pakistan",
        "adCount": 0,
        "aliases": [],
        "type": null,
        "hasBuilding": false,
        "trackID": "8067",
        "roles": null,
        "completionStatus": null,
        "hasChildren": false,
        "polygon": null,
        "objectID": "3926",
        "_highlightResult": {
            "name": {
                "value": "Ghulmet Nagar",
                "matchLevel": "none",
                "matchedWords": []
            }
        }
    },
    {
        "id": 3927,
        "name": "Gulmit",
        "name_l1": "گُلمِت",
        "externalID": "8068",
        "slug": "/Hunza_Gulmit-8068",
        "slug_l1": "/Hunza_Gulmit-8068",
        "_geoloc": {
            "lat": 36.389229,
            "lng": 74.868851
        },
        "geography": {
            "lat": 36.389229,
            "lng": 74.868851
        },
        "geo_point": [
            74.868851,
            36.389229
        ],
        "level": 3,
        "hierarchy": [
            {
                "id": 2,
                "level": 0,
                "externalID": "1521",
                "name": "Pakistan",
                "name_l1": "پاکستان",
                "slug": "/Pakistan-1521",
                "slug_l1": "/Pakistan-1521"
            },
            {
                "id": 8,
                "level": 1,
                "externalID": "1526",
                "name": "Gilgit Baltistan",
                "name_l1": "گلگت بلتستان",
                "slug": "/Gilgit_Baltistan-1526",
                "slug_l1": "/Gilgit_Baltistan-1526"
            },
            {
                "id": 79,
                "level": 2,
                "externalID": "1546",
                "name": "Hunza",
                "name_l1": "ہنزہ",
                "slug": "/Hunza-1546",
                "slug_l1": "/Hunza-1546"
            },
            {
                "id": 3927,
                "level": 3,
                "externalID": "8068",
                "name": "Gulmit",
                "name_l1": "گُلمِت",
                "slug": "/Hunza_Gulmit-8068",
                "slug_l1": "/Hunza_Gulmit-8068"
            }
        ],
        "hierarchyPath": "Gulmit Hunza Gilgit Baltistan Pakistan",
        "adCount": 0,
        "aliases": [],
        "type": null,
        "hasBuilding": false,
        "trackID": "8068",
        "roles": null,
        "completionStatus": null,
        "hasChildren": false,
        "polygon": null,
        "objectID": "3927",
        "_highlightResult": {
            "name": {
                "value": "Gulmit",
                "matchLevel": "none",
                "matchedWords": []
            }
        }
    },
    {
        "id": 3928,
        "name": "Haider Abad",
        "name_l1": "حیدر آباد",
        "externalID": "8069",
        "slug": "/Hunza_Haider_Abad-8069",
        "slug_l1": "/Hunza_Haider_Abad-8069",
        "_geoloc": {
            "lat": 36.314849,
            "lng": 74.646893
        },
        "geography": {
            "lat": 36.314849,
            "lng": 74.646893
        },
        "geo_point": [
            74.646893,
            36.314849
        ],
        "level": 3,
        "hierarchy": [
            {
                "id": 2,
                "level": 0,
                "externalID": "1521",
                "name": "Pakistan",
                "name_l1": "پاکستان",
                "slug": "/Pakistan-1521",
                "slug_l1": "/Pakistan-1521"
            },
            {
                "id": 8,
                "level": 1,
                "externalID": "1526",
                "name": "Gilgit Baltistan",
                "name_l1": "گلگت بلتستان",
                "slug": "/Gilgit_Baltistan-1526",
                "slug_l1": "/Gilgit_Baltistan-1526"
            },
            {
                "id": 79,
                "level": 2,
                "externalID": "1546",
                "name": "Hunza",
                "name_l1": "ہنزہ",
                "slug": "/Hunza-1546",
                "slug_l1": "/Hunza-1546"
            },
            {
                "id": 3928,
                "level": 3,
                "externalID": "8069",
                "name": "Haider Abad",
                "name_l1": "حیدر آباد",
                "slug": "/Hunza_Haider_Abad-8069",
                "slug_l1": "/Hunza_Haider_Abad-8069"
            }
        ],
        "hierarchyPath": "Haider Abad Hunza Gilgit Baltistan Pakistan",
        "adCount": 0,
        "aliases": [],
        "type": null,
        "hasBuilding": false,
        "trackID": "8069",
        "roles": null,
        "completionStatus": null,
        "hasChildren": false,
        "polygon": null,
        "objectID": "3928",
        "_highlightResult": {
            "name": {
                "value": "Haider Abad",
                "matchLevel": "none",
                "matchedWords": []
            }
        }
    },
    {
        "id": 3929,
        "name": "Hakal Shal",
        "name_l1": "ہکل شَل",
        "externalID": "8070",
        "slug": "/Hunza_Hakal_Shal-8070",
        "slug_l1": "/Hunza_Hakal_Shal-8070",
        "_geoloc": {
            "lat": 36.231535,
            "lng": 74.754009
        },
        "geography": {
            "lat": 36.231535,
            "lng": 74.754009
        },
        "geo_point": [
            74.754009,
            36.231535
        ],
        "level": 3,
        "hierarchy": [
            {
                "id": 2,
                "level": 0,
                "externalID": "1521",
                "name": "Pakistan",
                "name_l1": "پاکستان",
                "slug": "/Pakistan-1521",
                "slug_l1": "/Pakistan-1521"
            },
            {
                "id": 8,
                "level": 1,
                "externalID": "1526",
                "name": "Gilgit Baltistan",
                "name_l1": "گلگت بلتستان",
                "slug": "/Gilgit_Baltistan-1526",
                "slug_l1": "/Gilgit_Baltistan-1526"
            },
            {
                "id": 79,
                "level": 2,
                "externalID": "1546",
                "name": "Hunza",
                "name_l1": "ہنزہ",
                "slug": "/Hunza-1546",
                "slug_l1": "/Hunza-1546"
            },
            {
                "id": 3929,
                "level": 3,
                "externalID": "8070",
                "name": "Hakal Shal",
                "name_l1": "ہکل شَل",
                "slug": "/Hunza_Hakal_Shal-8070",
                "slug_l1": "/Hunza_Hakal_Shal-8070"
            }
        ],
        "hierarchyPath": "Hakal Shal Hunza Gilgit Baltistan Pakistan",
        "adCount": 0,
        "aliases": [],
        "type": null,
        "hasBuilding": false,
        "trackID": "8070",
        "roles": null,
        "completionStatus": null,
        "hasChildren": false,
        "polygon": null,
        "objectID": "3929",
        "_highlightResult": {
            "name": {
                "value": "Hakal Shal",
                "matchLevel": "none",
                "matchedWords": []
            }
        }
    },
    {
        "id": 3930,
        "name": "Hassan Abdal",
        "name_l1": "حسن ابدال",
        "externalID": "8071",
        "slug": "/Hunza_Hassan_Abdal-8071",
        "slug_l1": "/Hunza_Hassan_Abdal-8071",
        "_geoloc": {
            "lat": 36.304335,
            "lng": 74.674015
        },
        "geography": {
            "lat": 36.304335,
            "lng": 74.674015
        },
        "geo_point": [
            74.674015,
            36.304335
        ],
        "level": 3,
        "hierarchy": [
            {
                "id": 2,
                "level": 0,
                "externalID": "1521",
                "name": "Pakistan",
                "name_l1": "پاکستان",
                "slug": "/Pakistan-1521",
                "slug_l1": "/Pakistan-1521"
            },
            {
                "id": 8,
                "level": 1,
                "externalID": "1526",
                "name": "Gilgit Baltistan",
                "name_l1": "گلگت بلتستان",
                "slug": "/Gilgit_Baltistan-1526",
                "slug_l1": "/Gilgit_Baltistan-1526"
            },
            {
                "id": 79,
                "level": 2,
                "externalID": "1546",
                "name": "Hunza",
                "name_l1": "ہنزہ",
                "slug": "/Hunza-1546",
                "slug_l1": "/Hunza-1546"
            },
            {
                "id": 3930,
                "level": 3,
                "externalID": "8071",
                "name": "Hassan Abdal",
                "name_l1": "حسن ابدال",
                "slug": "/Hunza_Hassan_Abdal-8071",
                "slug_l1": "/Hunza_Hassan_Abdal-8071"
            }
        ],
        "hierarchyPath": "Hassan Abdal Hunza Gilgit Baltistan Pakistan",
        "adCount": 0,
        "aliases": [],
        "type": null,
        "hasBuilding": false,
        "trackID": "8071",
        "roles": null,
        "completionStatus": null,
        "hasChildren": false,
        "polygon": null,
        "objectID": "3930",
        "_highlightResult": {
            "name": {
                "value": "Hassan Abdal",
                "matchLevel": "none",
                "matchedWords": []
            }
        }
    },
    {
        "id": 3931,
        "name": "Hol Shal",
        "name_l1": "ہول شَل",
        "externalID": "8072",
        "slug": "/Hunza_Hol_Shal-8072",
        "slug_l1": "/Hunza_Hol_Shal-8072",
        "_geoloc": {
            "lat": 36.221565,
            "lng": 74.768772
        },
        "geography": {
            "lat": 36.221565,
            "lng": 74.768772
        },
        "geo_point": [
            74.768772,
            36.221565
        ],
        "level": 3,
        "hierarchy": [
            {
                "id": 2,
                "level": 0,
                "externalID": "1521",
                "name": "Pakistan",
                "name_l1": "پاکستان",
                "slug": "/Pakistan-1521",
                "slug_l1": "/Pakistan-1521"
            },
            {
                "id": 8,
                "level": 1,
                "externalID": "1526",
                "name": "Gilgit Baltistan",
                "name_l1": "گلگت بلتستان",
                "slug": "/Gilgit_Baltistan-1526",
                "slug_l1": "/Gilgit_Baltistan-1526"
            },
            {
                "id": 79,
                "level": 2,
                "externalID": "1546",
                "name": "Hunza",
                "name_l1": "ہنزہ",
                "slug": "/Hunza-1546",
                "slug_l1": "/Hunza-1546"
            },
            {
                "id": 3931,
                "level": 3,
                "externalID": "8072",
                "name": "Hol Shal",
                "name_l1": "ہول شَل",
                "slug": "/Hunza_Hol_Shal-8072",
                "slug_l1": "/Hunza_Hol_Shal-8072"
            }
        ],
        "hierarchyPath": "Hol Shal Hunza Gilgit Baltistan Pakistan",
        "adCount": 0,
        "aliases": [],
        "type": null,
        "hasBuilding": false,
        "trackID": "8072",
        "roles": null,
        "completionStatus": null,
        "hasChildren": false,
        "polygon": null,
        "objectID": "3931",
        "_highlightResult": {
            "name": {
                "value": "Hol Shal",
                "matchLevel": "none",
                "matchedWords": []
            }
        }
    },
    {
        "id": 3932,
        "name": "Humarri Bala",
        "name_l1": "ہُمڑی بالا",
        "externalID": "8073",
        "slug": "/Hunza_Humarri_Bala-8073",
        "slug_l1": "/Hunza_Humarri_Bala-8073",
        "_geoloc": {
            "lat": 36.27085,
            "lng": 74.705257
        },
        "geography": {
            "lat": 36.27085,
            "lng": 74.705257
        },
        "geo_point": [
            74.705257,
            36.27085
        ],
        "level": 3,
        "hierarchy": [
            {
                "id": 2,
                "level": 0,
                "externalID": "1521",
                "name": "Pakistan",
                "name_l1": "پاکستان",
                "slug": "/Pakistan-1521",
                "slug_l1": "/Pakistan-1521"
            },
            {
                "id": 8,
                "level": 1,
                "externalID": "1526",
                "name": "Gilgit Baltistan",
                "name_l1": "گلگت بلتستان",
                "slug": "/Gilgit_Baltistan-1526",
                "slug_l1": "/Gilgit_Baltistan-1526"
            },
            {
                "id": 79,
                "level": 2,
                "externalID": "1546",
                "name": "Hunza",
                "name_l1": "ہنزہ",
                "slug": "/Hunza-1546",
                "slug_l1": "/Hunza-1546"
            },
            {
                "id": 3932,
                "level": 3,
                "externalID": "8073",
                "name": "Humarri Bala",
                "name_l1": "ہُمڑی بالا",
                "slug": "/Hunza_Humarri_Bala-8073",
                "slug_l1": "/Hunza_Humarri_Bala-8073"
            }
        ],
        "hierarchyPath": "Humarri Bala Hunza Gilgit Baltistan Pakistan",
        "adCount": 0,
        "aliases": [],
        "type": null,
        "hasBuilding": false,
        "trackID": "8073",
        "roles": null,
        "completionStatus": null,
        "hasChildren": false,
        "polygon": null,
        "objectID": "3932",
        "_highlightResult": {
            "name": {
                "value": "Humarri Bala",
                "matchLevel": "none",
                "matchedWords": []
            }
        }
    },
    {
        "id": 3933,
        "name": "Humarri Khay",
        "name_l1": "ہُمڑی کھے",
        "externalID": "8074",
        "slug": "/Hunza_Humarri_Khay-8074",
        "slug_l1": "/Hunza_Humarri_Khay-8074",
        "_geoloc": {
            "lat": 36.276386,
            "lng": 74.713497
        },
        "geography": {
            "lat": 36.276386,
            "lng": 74.713497
        },
        "geo_point": [
            74.713497,
            36.276386
        ],
        "level": 3,
        "hierarchy": [
            {
                "id": 2,
                "level": 0,
                "externalID": "1521",
                "name": "Pakistan",
                "name_l1": "پاکستان",
                "slug": "/Pakistan-1521",
                "slug_l1": "/Pakistan-1521"
            },
            {
                "id": 8,
                "level": 1,
                "externalID": "1526",
                "name": "Gilgit Baltistan",
                "name_l1": "گلگت بلتستان",
                "slug": "/Gilgit_Baltistan-1526",
                "slug_l1": "/Gilgit_Baltistan-1526"
            },
            {
                "id": 79,
                "level": 2,
                "externalID": "1546",
                "name": "Hunza",
                "name_l1": "ہنزہ",
                "slug": "/Hunza-1546",
                "slug_l1": "/Hunza-1546"
            },
            {
                "id": 3933,
                "level": 3,
                "externalID": "8074",
                "name": "Humarri Khay",
                "name_l1": "ہُمڑی کھے",
                "slug": "/Hunza_Humarri_Khay-8074",
                "slug_l1": "/Hunza_Humarri_Khay-8074"
            }
        ],
        "hierarchyPath": "Humarri Khay Hunza Gilgit Baltistan Pakistan",
        "adCount": 0,
        "aliases": [],
        "type": null,
        "hasBuilding": false,
        "trackID": "8074",
        "roles": null,
        "completionStatus": null,
        "hasChildren": false,
        "polygon": null,
        "objectID": "3933",
        "_highlightResult": {
            "name": {
                "value": "Humarri Khay",
                "matchLevel": "none",
                "matchedWords": []
            }
        }
    },
    {
        "id": 3934,
        "name": "Jamal Abad",
        "name_l1": "جمال آباد",
        "externalID": "8075",
        "slug": "/Hunza_Jamal_Abad-8075",
        "slug_l1": "/Hunza_Jamal_Abad-8075",
        "_geoloc": {
            "lat": 36.619937,
            "lng": 74.863358
        },
        "geography": {
            "lat": 36.619937,
            "lng": 74.863358
        },
        "geo_point": [
            74.863358,
            36.619937
        ],
        "level": 3,
        "hierarchy": [
            {
                "id": 2,
                "level": 0,
                "externalID": "1521",
                "name": "Pakistan",
                "name_l1": "پاکستان",
                "slug": "/Pakistan-1521",
                "slug_l1": "/Pakistan-1521"
            },
            {
                "id": 8,
                "level": 1,
                "externalID": "1526",
                "name": "Gilgit Baltistan",
                "name_l1": "گلگت بلتستان",
                "slug": "/Gilgit_Baltistan-1526",
                "slug_l1": "/Gilgit_Baltistan-1526"
            },
            {
                "id": 79,
                "level": 2,
                "externalID": "1546",
                "name": "Hunza",
                "name_l1": "ہنزہ",
                "slug": "/Hunza-1546",
                "slug_l1": "/Hunza-1546"
            },
            {
                "id": 3934,
                "level": 3,
                "externalID": "8075",
                "name": "Jamal Abad",
                "name_l1": "جمال آباد",
                "slug": "/Hunza_Jamal_Abad-8075",
                "slug_l1": "/Hunza_Jamal_Abad-8075"
            }
        ],
        "hierarchyPath": "Jamal Abad Hunza Gilgit Baltistan Pakistan",
        "adCount": 0,
        "aliases": [],
        "type": null,
        "hasBuilding": false,
        "trackID": "8075",
        "roles": null,
        "completionStatus": null,
        "hasChildren": false,
        "polygon": null,
        "objectID": "3934",
        "_highlightResult": {
            "name": {
                "value": "Jamal Abad",
                "matchLevel": "none",
                "matchedWords": []
            }
        }
    },
    {
        "id": 3935,
        "name": "Jator Khan",
        "name_l1": "جتور خان",
        "externalID": "8076",
        "slug": "/Hunza_Jator_Khan-8076",
        "slug_l1": "/Hunza_Jator_Khan-8076",
        "_geoloc": {
            "lat": 36.308762,
            "lng": 74.646893
        },
        "geography": {
            "lat": 36.308762,
            "lng": 74.646893
        },
        "geo_point": [
            74.646893,
            36.308762
        ],
        "level": 3,
        "hierarchy": [
            {
                "id": 2,
                "level": 0,
                "externalID": "1521",
                "name": "Pakistan",
                "name_l1": "پاکستان",
                "slug": "/Pakistan-1521",
                "slug_l1": "/Pakistan-1521"
            },
            {
                "id": 8,
                "level": 1,
                "externalID": "1526",
                "name": "Gilgit Baltistan",
                "name_l1": "گلگت بلتستان",
                "slug": "/Gilgit_Baltistan-1526",
                "slug_l1": "/Gilgit_Baltistan-1526"
            },
            {
                "id": 79,
                "level": 2,
                "externalID": "1546",
                "name": "Hunza",
                "name_l1": "ہنزہ",
                "slug": "/Hunza-1546",
                "slug_l1": "/Hunza-1546"
            },
            {
                "id": 3935,
                "level": 3,
                "externalID": "8076",
                "name": "Jator Khan",
                "name_l1": "جتور خان",
                "slug": "/Hunza_Jator_Khan-8076",
                "slug_l1": "/Hunza_Jator_Khan-8076"
            }
        ],
        "hierarchyPath": "Jator Khan Hunza Gilgit Baltistan Pakistan",
        "adCount": 0,
        "aliases": [],
        "type": null,
        "hasBuilding": false,
        "trackID": "8076",
        "roles": null,
        "completionStatus": null,
        "hasChildren": false,
        "polygon": null,
        "objectID": "3935",
        "_highlightResult": {
            "name": {
                "value": "Jator Khan",
                "matchLevel": "none",
                "matchedWords": []
            }
        }
    },
    {
        "id": 3936,
        "name": "Karakoram Highway",
        "name_l1": "قراقرم ہائی وے",
        "externalID": "8077",
        "slug": "/Hunza_Karakoram_Highway-8077",
        "slug_l1": "/Hunza_Karakoram_Highway-8077",
        "_geoloc": {
            "lat": 36.294582,
            "lng": 74.728818
        },
        "geography": {
            "lat": 36.294582,
            "lng": 74.728818
        },
        "geo_point": [
            74.728818,
            36.294582
        ],
        "level": 3,
        "hierarchy": [
            {
                "id": 2,
                "level": 0,
                "externalID": "1521",
                "name": "Pakistan",
                "name_l1": "پاکستان",
                "slug": "/Pakistan-1521",
                "slug_l1": "/Pakistan-1521"
            },
            {
                "id": 8,
                "level": 1,
                "externalID": "1526",
                "name": "Gilgit Baltistan",
                "name_l1": "گلگت بلتستان",
                "slug": "/Gilgit_Baltistan-1526",
                "slug_l1": "/Gilgit_Baltistan-1526"
            },
            {
                "id": 79,
                "level": 2,
                "externalID": "1546",
                "name": "Hunza",
                "name_l1": "ہنزہ",
                "slug": "/Hunza-1546",
                "slug_l1": "/Hunza-1546"
            },
            {
                "id": 3936,
                "level": 3,
                "externalID": "8077",
                "name": "Karakoram Highway",
                "name_l1": "قراقرم ہائی وے",
                "slug": "/Hunza_Karakoram_Highway-8077",
                "slug_l1": "/Hunza_Karakoram_Highway-8077"
            }
        ],
        "hierarchyPath": "Karakoram Highway Hunza Gilgit Baltistan Pakistan",
        "adCount": 0,
        "aliases": [],
        "type": null,
        "hasBuilding": false,
        "trackID": "8077",
        "roles": null,
        "completionStatus": null,
        "hasChildren": false,
        "polygon": null,
        "objectID": "3936",
        "_highlightResult": {
            "name": {
                "value": "Karakoram Highway",
                "matchLevel": "none",
                "matchedWords": []
            }
        }
    },
    {
        "id": 3937,
        "name": "Karimabad",
        "name_l1": "کریم آباد",
        "externalID": "8078",
        "slug": "/Hunza_Karimabad-8078",
        "slug_l1": "/Hunza_Karimabad-8078",
        "_geoloc": {
            "lat": 36.32453,
            "lng": 74.657879
        },
        "geography": {
            "lat": 36.32453,
            "lng": 74.657879
        },
        "geo_point": [
            74.657879,
            36.32453
        ],
        "level": 3,
        "hierarchy": [
            {
                "id": 2,
                "level": 0,
                "externalID": "1521",
                "name": "Pakistan",
                "name_l1": "پاکستان",
                "slug": "/Pakistan-1521",
                "slug_l1": "/Pakistan-1521"
            },
            {
                "id": 8,
                "level": 1,
                "externalID": "1526",
                "name": "Gilgit Baltistan",
                "name_l1": "گلگت بلتستان",
                "slug": "/Gilgit_Baltistan-1526",
                "slug_l1": "/Gilgit_Baltistan-1526"
            },
            {
                "id": 79,
                "level": 2,
                "externalID": "1546",
                "name": "Hunza",
                "name_l1": "ہنزہ",
                "slug": "/Hunza-1546",
                "slug_l1": "/Hunza-1546"
            },
            {
                "id": 3937,
                "level": 3,
                "externalID": "8078",
                "name": "Karimabad",
                "name_l1": "کریم آباد",
                "slug": "/Hunza_Karimabad-8078",
                "slug_l1": "/Hunza_Karimabad-8078"
            }
        ],
        "hierarchyPath": "Karimabad Hunza Gilgit Baltistan Pakistan",
        "adCount": 0,
        "aliases": [],
        "type": null,
        "hasBuilding": false,
        "trackID": "8078",
        "roles": null,
        "completionStatus": null,
        "hasChildren": false,
        "polygon": null,
        "objectID": "3937",
        "_highlightResult": {
            "name": {
                "value": "Karimabad",
                "matchLevel": "none",
                "matchedWords": []
            }
        }
    },
    {
        "id": 3938,
        "name": "Khana Abad Road",
        "name_l1": "کھنہ آباد روڈ",
        "externalID": "8079",
        "slug": "/Hunza_Khana_Abad_Road-8079",
        "slug_l1": "/Hunza_Khana_Abad_Road-8079",
        "_geoloc": {
            "lat": 36.248703,
            "lng": 74.468594
        },
        "geography": {
            "lat": 36.248703,
            "lng": 74.468594
        },
        "geo_point": [
            74.468594,
            36.248703
        ],
        "level": 3,
        "hierarchy": [
            {
                "id": 2,
                "level": 0,
                "externalID": "1521",
                "name": "Pakistan",
                "name_l1": "پاکستان",
                "slug": "/Pakistan-1521",
                "slug_l1": "/Pakistan-1521"
            },
            {
                "id": 8,
                "level": 1,
                "externalID": "1526",
                "name": "Gilgit Baltistan",
                "name_l1": "گلگت بلتستان",
                "slug": "/Gilgit_Baltistan-1526",
                "slug_l1": "/Gilgit_Baltistan-1526"
            },
            {
                "id": 79,
                "level": 2,
                "externalID": "1546",
                "name": "Hunza",
                "name_l1": "ہنزہ",
                "slug": "/Hunza-1546",
                "slug_l1": "/Hunza-1546"
            },
            {
                "id": 3938,
                "level": 3,
                "externalID": "8079",
                "name": "Khana Abad Road",
                "name_l1": "کھنہ آباد روڈ",
                "slug": "/Hunza_Khana_Abad_Road-8079",
                "slug_l1": "/Hunza_Khana_Abad_Road-8079"
            }
        ],
        "hierarchyPath": "Khana Abad Road Hunza Gilgit Baltistan Pakistan",
        "adCount": 0,
        "aliases": [],
        "type": null,
        "hasBuilding": false,
        "trackID": "8079",
        "roles": null,
        "completionStatus": null,
        "hasChildren": false,
        "polygon": null,
        "objectID": "3938",
        "_highlightResult": {
            "name": {
                "value": "Khana Abad Road",
                "matchLevel": "none",
                "matchedWords": []
            }
        }
    },
    {
        "id": 3939,
        "name": "Mehdi Abad",
        "name_l1": "مہدی آباد",
        "externalID": "8080",
        "slug": "/Hunza_Mehdi_Abad-8080",
        "slug_l1": "/Hunza_Mehdi_Abad-8080",
        "_geoloc": {
            "lat": 36.270573,
            "lng": 74.753666
        },
        "geography": {
            "lat": 36.270573,
            "lng": 74.753666
        },
        "geo_point": [
            74.753666,
            36.270573
        ],
        "level": 3,
        "hierarchy": [
            {
                "id": 2,
                "level": 0,
                "externalID": "1521",
                "name": "Pakistan",
                "name_l1": "پاکستان",
                "slug": "/Pakistan-1521",
                "slug_l1": "/Pakistan-1521"
            },
            {
                "id": 8,
                "level": 1,
                "externalID": "1526",
                "name": "Gilgit Baltistan",
                "name_l1": "گلگت بلتستان",
                "slug": "/Gilgit_Baltistan-1526",
                "slug_l1": "/Gilgit_Baltistan-1526"
            },
            {
                "id": 79,
                "level": 2,
                "externalID": "1546",
                "name": "Hunza",
                "name_l1": "ہنزہ",
                "slug": "/Hunza-1546",
                "slug_l1": "/Hunza-1546"
            },
            {
                "id": 3939,
                "level": 3,
                "externalID": "8080",
                "name": "Mehdi Abad",
                "name_l1": "مہدی آباد",
                "slug": "/Hunza_Mehdi_Abad-8080",
                "slug_l1": "/Hunza_Mehdi_Abad-8080"
            }
        ],
        "hierarchyPath": "Mehdi Abad Hunza Gilgit Baltistan Pakistan",
        "adCount": 0,
        "aliases": [],
        "type": null,
        "hasBuilding": false,
        "trackID": "8080",
        "roles": null,
        "completionStatus": null,
        "hasChildren": false,
        "polygon": null,
        "objectID": "3939",
        "_highlightResult": {
            "name": {
                "value": "Mehdi Abad",
                "matchLevel": "none",
                "matchedWords": []
            }
        }
    },
    {
        "id": 3940,
        "name": "Miachar Nagar",
        "name_l1": "میاچر نگر",
        "externalID": "8081",
        "slug": "/Hunza_Miachar_Nagar-8081",
        "slug_l1": "/Hunza_Miachar_Nagar-8081",
        "_geoloc": {
            "lat": 36.249811,
            "lng": 74.577141
        },
        "geography": {
            "lat": 36.249811,
            "lng": 74.577141
        },
        "geo_point": [
            74.577141,
            36.249811
        ],
        "level": 3,
        "hierarchy": [
            {
                "id": 2,
                "level": 0,
                "externalID": "1521",
                "name": "Pakistan",
                "name_l1": "پاکستان",
                "slug": "/Pakistan-1521",
                "slug_l1": "/Pakistan-1521"
            },
            {
                "id": 8,
                "level": 1,
                "externalID": "1526",
                "name": "Gilgit Baltistan",
                "name_l1": "گلگت بلتستان",
                "slug": "/Gilgit_Baltistan-1526",
                "slug_l1": "/Gilgit_Baltistan-1526"
            },
            {
                "id": 79,
                "level": 2,
                "externalID": "1546",
                "name": "Hunza",
                "name_l1": "ہنزہ",
                "slug": "/Hunza-1546",
                "slug_l1": "/Hunza-1546"
            },
            {
                "id": 3940,
                "level": 3,
                "externalID": "8081",
                "name": "Miachar Nagar",
                "name_l1": "میاچر نگر",
                "slug": "/Hunza_Miachar_Nagar-8081",
                "slug_l1": "/Hunza_Miachar_Nagar-8081"
            }
        ],
        "hierarchyPath": "Miachar Nagar Hunza Gilgit Baltistan Pakistan",
        "adCount": 0,
        "aliases": [],
        "type": null,
        "hasBuilding": false,
        "trackID": "8081",
        "roles": null,
        "completionStatus": null,
        "hasChildren": false,
        "polygon": null,
        "objectID": "3940",
        "_highlightResult": {
            "name": {
                "value": "Miachar Nagar",
                "matchLevel": "none",
                "matchedWords": []
            }
        }
    },
    {
        "id": 3941,
        "name": "Minapin Nagar",
        "name_l1": "مِناپِن نگر",
        "externalID": "8082",
        "slug": "/Hunza_Minapin_Nagar-8082",
        "slug_l1": "/Hunza_Minapin_Nagar-8082",
        "_geoloc": {
            "lat": 36.250918,
            "lng": 74.537315
        },
        "geography": {
            "lat": 36.250918,
            "lng": 74.537315
        },
        "geo_point": [
            74.537315,
            36.250918
        ],
        "level": 3,
        "hierarchy": [
            {
                "id": 2,
                "level": 0,
                "externalID": "1521",
                "name": "Pakistan",
                "name_l1": "پاکستان",
                "slug": "/Pakistan-1521",
                "slug_l1": "/Pakistan-1521"
            },
            {
                "id": 8,
                "level": 1,
                "externalID": "1526",
                "name": "Gilgit Baltistan",
                "name_l1": "گلگت بلتستان",
                "slug": "/Gilgit_Baltistan-1526",
                "slug_l1": "/Gilgit_Baltistan-1526"
            },
            {
                "id": 79,
                "level": 2,
                "externalID": "1546",
                "name": "Hunza",
                "name_l1": "ہنزہ",
                "slug": "/Hunza-1546",
                "slug_l1": "/Hunza-1546"
            },
            {
                "id": 3941,
                "level": 3,
                "externalID": "8082",
                "name": "Minapin Nagar",
                "name_l1": "مِناپِن نگر",
                "slug": "/Hunza_Minapin_Nagar-8082",
                "slug_l1": "/Hunza_Minapin_Nagar-8082"
            }
        ],
        "hierarchyPath": "Minapin Nagar Hunza Gilgit Baltistan Pakistan",
        "adCount": 0,
        "aliases": [],
        "type": null,
        "hasBuilding": false,
        "trackID": "8082",
        "roles": null,
        "completionStatus": null,
        "hasChildren": false,
        "polygon": null,
        "objectID": "3941",
        "_highlightResult": {
            "name": {
                "value": "Minapin Nagar",
                "matchLevel": "none",
                "matchedWords": []
            }
        }
    },
    {
        "id": 3942,
        "name": "Mumtaz Abad",
        "name_l1": "ممتاز آباد",
        "externalID": "8083",
        "slug": "/Hunza_Mumtaz_Abad-8083",
        "slug_l1": "/Hunza_Mumtaz_Abad-8083",
        "_geoloc": {
            "lat": 36.279707,
            "lng": 74.60186
        },
        "geography": {
            "lat": 36.279707,
            "lng": 74.60186
        },
        "geo_point": [
            74.60186,
            36.279707
        ],
        "level": 3,
        "hierarchy": [
            {
                "id": 2,
                "level": 0,
                "externalID": "1521",
                "name": "Pakistan",
                "name_l1": "پاکستان",
                "slug": "/Pakistan-1521",
                "slug_l1": "/Pakistan-1521"
            },
            {
                "id": 8,
                "level": 1,
                "externalID": "1526",
                "name": "Gilgit Baltistan",
                "name_l1": "گلگت بلتستان",
                "slug": "/Gilgit_Baltistan-1526",
                "slug_l1": "/Gilgit_Baltistan-1526"
            },
            {
                "id": 79,
                "level": 2,
                "externalID": "1546",
                "name": "Hunza",
                "name_l1": "ہنزہ",
                "slug": "/Hunza-1546",
                "slug_l1": "/Hunza-1546"
            },
            {
                "id": 3942,
                "level": 3,
                "externalID": "8083",
                "name": "Mumtaz Abad",
                "name_l1": "ممتاز آباد",
                "slug": "/Hunza_Mumtaz_Abad-8083",
                "slug_l1": "/Hunza_Mumtaz_Abad-8083"
            }
        ],
        "hierarchyPath": "Mumtaz Abad Hunza Gilgit Baltistan Pakistan",
        "adCount": 0,
        "aliases": [],
        "type": null,
        "hasBuilding": false,
        "trackID": "8083",
        "roles": null,
        "completionStatus": null,
        "hasChildren": false,
        "polygon": null,
        "objectID": "3942",
        "_highlightResult": {
            "name": {
                "value": "Mumtaz Abad",
                "matchLevel": "none",
                "matchedWords": []
            }
        }
    },
    {
        "id": 3944,
        "name": "Nagar - Hisper - Hopar Road",
        "name_l1": "نگر ۔ ہیسپر ۔ ہوپر روڈ",
        "externalID": "8085",
        "slug": "/Hunza_Nagar_Hisper_Hopar_Road-8085",
        "slug_l1": "/Hunza_Nagar_Hisper_Hopar_Road-8085",
        "_geoloc": {
            "lat": 36.219211,
            "lng": 74.839182
        },
        "geography": {
            "lat": 36.219211,
            "lng": 74.839182
        },
        "geo_point": [
            74.839182,
            36.219211
        ],
        "level": 3,
        "hierarchy": [
            {
                "id": 2,
                "level": 0,
                "externalID": "1521",
                "name": "Pakistan",
                "name_l1": "پاکستان",
                "slug": "/Pakistan-1521",
                "slug_l1": "/Pakistan-1521"
            },
            {
                "id": 8,
                "level": 1,
                "externalID": "1526",
                "name": "Gilgit Baltistan",
                "name_l1": "گلگت بلتستان",
                "slug": "/Gilgit_Baltistan-1526",
                "slug_l1": "/Gilgit_Baltistan-1526"
            },
            {
                "id": 79,
                "level": 2,
                "externalID": "1546",
                "name": "Hunza",
                "name_l1": "ہنزہ",
                "slug": "/Hunza-1546",
                "slug_l1": "/Hunza-1546"
            },
            {
                "id": 3944,
                "level": 3,
                "externalID": "8085",
                "name": "Nagar - Hisper - Hopar Road",
                "name_l1": "نگر ۔ ہیسپر ۔ ہوپر روڈ",
                "slug": "/Hunza_Nagar_Hisper_Hopar_Road-8085",
                "slug_l1": "/Hunza_Nagar_Hisper_Hopar_Road-8085"
            }
        ],
        "hierarchyPath": "Nagar - Hisper - Hopar Road Hunza Gilgit Baltistan Pakistan",
        "adCount": 0,
        "aliases": [],
        "type": null,
        "hasBuilding": false,
        "trackID": "8085",
        "roles": null,
        "completionStatus": null,
        "hasChildren": false,
        "polygon": null,
        "objectID": "3944",
        "_highlightResult": {
            "name": {
                "value": "Nagar - Hisper - Hopar Road",
                "matchLevel": "none",
                "matchedWords": []
            }
        }
    },
    {
        "id": 3943,
        "name": "Nagar Khas",
        "name_l1": "نگر خاص",
        "externalID": "8084",
        "slug": "/Hunza_Nagar_Khas-8084",
        "slug_l1": "/Hunza_Nagar_Khas-8084",
        "_geoloc": {
            "lat": 36.269466,
            "lng": 74.73032
        },
        "geography": {
            "lat": 36.269466,
            "lng": 74.73032
        },
        "geo_point": [
            74.73032,
            36.269466
        ],
        "level": 3,
        "hierarchy": [
            {
                "id": 2,
                "level": 0,
                "externalID": "1521",
                "name": "Pakistan",
                "name_l1": "پاکستان",
                "slug": "/Pakistan-1521",
                "slug_l1": "/Pakistan-1521"
            },
            {
                "id": 8,
                "level": 1,
                "externalID": "1526",
                "name": "Gilgit Baltistan",
                "name_l1": "گلگت بلتستان",
                "slug": "/Gilgit_Baltistan-1526",
                "slug_l1": "/Gilgit_Baltistan-1526"
            },
            {
                "id": 79,
                "level": 2,
                "externalID": "1546",
                "name": "Hunza",
                "name_l1": "ہنزہ",
                "slug": "/Hunza-1546",
                "slug_l1": "/Hunza-1546"
            },
            {
                "id": 3943,
                "level": 3,
                "externalID": "8084",
                "name": "Nagar Khas",
                "name_l1": "نگر خاص",
                "slug": "/Hunza_Nagar_Khas-8084",
                "slug_l1": "/Hunza_Nagar_Khas-8084"
            }
        ],
        "hierarchyPath": "Nagar Khas Hunza Gilgit Baltistan Pakistan",
        "adCount": 0,
        "aliases": [],
        "type": null,
        "hasBuilding": false,
        "trackID": "8084",
        "roles": null,
        "completionStatus": null,
        "hasChildren": false,
        "polygon": null,
        "objectID": "3943",
        "_highlightResult": {
            "name": {
                "value": "Nagar Khas",
                "matchLevel": "none",
                "matchedWords": []
            }
        }
    },
    {
        "id": 3945,
        "name": "Nazim Abad",
        "name_l1": "ناظم آباد",
        "externalID": "8086",
        "slug": "/Hunza_Nazim_Abad-8086",
        "slug_l1": "/Hunza_Nazim_Abad-8086",
        "_geoloc": {
            "lat": 36.66952,
            "lng": 74.845734
        },
        "geography": {
            "lat": 36.66952,
            "lng": 74.845734
        },
        "geo_point": [
            74.845734,
            36.66952
        ],
        "level": 3,
        "hierarchy": [
            {
                "id": 2,
                "level": 0,
                "externalID": "1521",
                "name": "Pakistan",
                "name_l1": "پاکستان",
                "slug": "/Pakistan-1521",
                "slug_l1": "/Pakistan-1521"
            },
            {
                "id": 8,
                "level": 1,
                "externalID": "1526",
                "name": "Gilgit Baltistan",
                "name_l1": "گلگت بلتستان",
                "slug": "/Gilgit_Baltistan-1526",
                "slug_l1": "/Gilgit_Baltistan-1526"
            },
            {
                "id": 79,
                "level": 2,
                "externalID": "1546",
                "name": "Hunza",
                "name_l1": "ہنزہ",
                "slug": "/Hunza-1546",
                "slug_l1": "/Hunza-1546"
            },
            {
                "id": 3945,
                "level": 3,
                "externalID": "8086",
                "name": "Nazim Abad",
                "name_l1": "ناظم آباد",
                "slug": "/Hunza_Nazim_Abad-8086",
                "slug_l1": "/Hunza_Nazim_Abad-8086"
            }
        ],
        "hierarchyPath": "Nazim Abad Hunza Gilgit Baltistan Pakistan",
        "adCount": 0,
        "aliases": [],
        "type": null,
        "hasBuilding": false,
        "trackID": "8086",
        "roles": null,
        "completionStatus": null,
        "hasChildren": false,
        "polygon": null,
        "objectID": "3945",
        "_highlightResult": {
            "name": {
                "value": "Nazim Abad",
                "matchLevel": "none",
                "matchedWords": []
            }
        }
    },
    {
        "id": 3946,
        "name": "Others",
        "name_l1": "دیگر",
        "externalID": "8087",
        "slug": "/Hunza_Others-8087",
        "slug_l1": "/Hunza_Others-8087",
        "_geoloc": {
            "lat": 36.3167,
            "lng": 74.65
        },
        "geography": {
            "lat": 36.3167,
            "lng": 74.65
        },
        "geo_point": [
            74.65,
            36.3167
        ],
        "level": 3,
        "hierarchy": [
            {
                "id": 2,
                "level": 0,
                "externalID": "1521",
                "name": "Pakistan",
                "name_l1": "پاکستان",
                "slug": "/Pakistan-1521",
                "slug_l1": "/Pakistan-1521"
            },
            {
                "id": 8,
                "level": 1,
                "externalID": "1526",
                "name": "Gilgit Baltistan",
                "name_l1": "گلگت بلتستان",
                "slug": "/Gilgit_Baltistan-1526",
                "slug_l1": "/Gilgit_Baltistan-1526"
            },
            {
                "id": 79,
                "level": 2,
                "externalID": "1546",
                "name": "Hunza",
                "name_l1": "ہنزہ",
                "slug": "/Hunza-1546",
                "slug_l1": "/Hunza-1546"
            },
            {
                "id": 3946,
                "level": 3,
                "externalID": "8087",
                "name": "Others",
                "name_l1": "دیگر",
                "slug": "/Hunza_Others-8087",
                "slug_l1": "/Hunza_Others-8087"
            }
        ],
        "hierarchyPath": "Others Hunza Gilgit Baltistan Pakistan",
        "adCount": 0,
        "aliases": [],
        "type": null,
        "hasBuilding": false,
        "trackID": "8087",
        "roles": null,
        "completionStatus": null,
        "hasChildren": false,
        "polygon": null,
        "objectID": "3946",
        "_highlightResult": {
            "name": {
                "value": "Others",
                "matchLevel": "none",
                "matchedWords": []
            }
        }
    },
    {
        "id": 3947,
        "name": "Phakkar Nagar Road",
        "name_l1": "پکھر نگر روڈ",
        "externalID": "8088",
        "slug": "/Hunza_Phakkar_Nagar_Road-8088",
        "slug_l1": "/Hunza_Phakkar_Nagar_Road-8088",
        "_geoloc": {
            "lat": 36.266352,
            "lng": 74.589994
        },
        "geography": {
            "lat": 36.266352,
            "lng": 74.589994
        },
        "geo_point": [
            74.589994,
            36.266352
        ],
        "level": 3,
        "hierarchy": [
            {
                "id": 2,
                "level": 0,
                "externalID": "1521",
                "name": "Pakistan",
                "name_l1": "پاکستان",
                "slug": "/Pakistan-1521",
                "slug_l1": "/Pakistan-1521"
            },
            {
                "id": 8,
                "level": 1,
                "externalID": "1526",
                "name": "Gilgit Baltistan",
                "name_l1": "گلگت بلتستان",
                "slug": "/Gilgit_Baltistan-1526",
                "slug_l1": "/Gilgit_Baltistan-1526"
            },
            {
                "id": 79,
                "level": 2,
                "externalID": "1546",
                "name": "Hunza",
                "name_l1": "ہنزہ",
                "slug": "/Hunza-1546",
                "slug_l1": "/Hunza-1546"
            },
            {
                "id": 3947,
                "level": 3,
                "externalID": "8088",
                "name": "Phakkar Nagar Road",
                "name_l1": "پکھر نگر روڈ",
                "slug": "/Hunza_Phakkar_Nagar_Road-8088",
                "slug_l1": "/Hunza_Phakkar_Nagar_Road-8088"
            }
        ],
        "hierarchyPath": "Phakkar Nagar Road Hunza Gilgit Baltistan Pakistan",
        "adCount": 0,
        "aliases": [],
        "type": null,
        "hasBuilding": false,
        "trackID": "8088",
        "roles": null,
        "completionStatus": null,
        "hasChildren": false,
        "polygon": null,
        "objectID": "3947",
        "_highlightResult": {
            "name": {
                "value": "Phakkar Nagar Road",
                "matchLevel": "none",
                "matchedWords": []
            }
        }
    },
    {
        "id": 3948,
        "name": "Salman Abad",
        "name_l1": "سلمان آباد",
        "externalID": "8089",
        "slug": "/Hunza_Salman_Abad-8089",
        "slug_l1": "/Hunza_Salman_Abad-8089",
        "_geoloc": {
            "lat": 36.310699,
            "lng": 74.778042
        },
        "geography": {
            "lat": 36.310699,
            "lng": 74.778042
        },
        "geo_point": [
            74.778042,
            36.310699
        ],
        "level": 3,
        "hierarchy": [
            {
                "id": 2,
                "level": 0,
                "externalID": "1521",
                "name": "Pakistan",
                "name_l1": "پاکستان",
                "slug": "/Pakistan-1521",
                "slug_l1": "/Pakistan-1521"
            },
            {
                "id": 8,
                "level": 1,
                "externalID": "1526",
                "name": "Gilgit Baltistan",
                "name_l1": "گلگت بلتستان",
                "slug": "/Gilgit_Baltistan-1526",
                "slug_l1": "/Gilgit_Baltistan-1526"
            },
            {
                "id": 79,
                "level": 2,
                "externalID": "1546",
                "name": "Hunza",
                "name_l1": "ہنزہ",
                "slug": "/Hunza-1546",
                "slug_l1": "/Hunza-1546"
            },
            {
                "id": 3948,
                "level": 3,
                "externalID": "8089",
                "name": "Salman Abad",
                "name_l1": "سلمان آباد",
                "slug": "/Hunza_Salman_Abad-8089",
                "slug_l1": "/Hunza_Salman_Abad-8089"
            }
        ],
        "hierarchyPath": "Salman Abad Hunza Gilgit Baltistan Pakistan",
        "adCount": 0,
        "aliases": [],
        "type": null,
        "hasBuilding": false,
        "trackID": "8089",
        "roles": null,
        "completionStatus": null,
        "hasChildren": false,
        "polygon": null,
        "objectID": "3948",
        "_highlightResult": {
            "name": {
                "value": "Salman Abad",
                "matchLevel": "none",
                "matchedWords": []
            }
        }
    },
    {
        "id": 3949,
        "name": "Sarat",
        "name_l1": "سرت",
        "externalID": "8090",
        "slug": "/Hunza_Sarat-8090",
        "slug_l1": "/Hunza_Sarat-8090",
        "_geoloc": {
            "lat": 36.310699,
            "lng": 74.778042
        },
        "geography": {
            "lat": 36.310699,
            "lng": 74.778042
        },
        "geo_point": [
            74.778042,
            36.310699
        ],
        "level": 3,
        "hierarchy": [
            {
                "id": 2,
                "level": 0,
                "externalID": "1521",
                "name": "Pakistan",
                "name_l1": "پاکستان",
                "slug": "/Pakistan-1521",
                "slug_l1": "/Pakistan-1521"
            },
            {
                "id": 8,
                "level": 1,
                "externalID": "1526",
                "name": "Gilgit Baltistan",
                "name_l1": "گلگت بلتستان",
                "slug": "/Gilgit_Baltistan-1526",
                "slug_l1": "/Gilgit_Baltistan-1526"
            },
            {
                "id": 79,
                "level": 2,
                "externalID": "1546",
                "name": "Hunza",
                "name_l1": "ہنزہ",
                "slug": "/Hunza-1546",
                "slug_l1": "/Hunza-1546"
            },
            {
                "id": 3949,
                "level": 3,
                "externalID": "8090",
                "name": "Sarat",
                "name_l1": "سرت",
                "slug": "/Hunza_Sarat-8090",
                "slug_l1": "/Hunza_Sarat-8090"
            }
        ],
        "hierarchyPath": "Sarat Hunza Gilgit Baltistan Pakistan",
        "adCount": 0,
        "aliases": [],
        "type": null,
        "hasBuilding": false,
        "trackID": "8090",
        "roles": null,
        "completionStatus": null,
        "hasChildren": false,
        "polygon": null,
        "objectID": "3949",
        "_highlightResult": {
            "name": {
                "value": "Sarat",
                "matchLevel": "none",
                "matchedWords": []
            }
        }
    },
    {
        "id": 3950,
        "name": "Sas Valley Road",
        "name_l1": "ساس ویلی روڈ",
        "externalID": "8091",
        "slug": "/Hunza_Sas_Valley_Road-8091",
        "slug_l1": "/Hunza_Sas_Valley_Road-8091",
        "_geoloc": {
            "lat": 36.29562,
            "lng": 74.626772
        },
        "geography": {
            "lat": 36.29562,
            "lng": 74.626772
        },
        "geo_point": [
            74.626772,
            36.29562
        ],
        "level": 3,
        "hierarchy": [
            {
                "id": 2,
                "level": 0,
                "externalID": "1521",
                "name": "Pakistan",
                "name_l1": "پاکستان",
                "slug": "/Pakistan-1521",
                "slug_l1": "/Pakistan-1521"
            },
            {
                "id": 8,
                "level": 1,
                "externalID": "1526",
                "name": "Gilgit Baltistan",
                "name_l1": "گلگت بلتستان",
                "slug": "/Gilgit_Baltistan-1526",
                "slug_l1": "/Gilgit_Baltistan-1526"
            },
            {
                "id": 79,
                "level": 2,
                "externalID": "1546",
                "name": "Hunza",
                "name_l1": "ہنزہ",
                "slug": "/Hunza-1546",
                "slug_l1": "/Hunza-1546"
            },
            {
                "id": 3950,
                "level": 3,
                "externalID": "8091",
                "name": "Sas Valley Road",
                "name_l1": "ساس ویلی روڈ",
                "slug": "/Hunza_Sas_Valley_Road-8091",
                "slug_l1": "/Hunza_Sas_Valley_Road-8091"
            }
        ],
        "hierarchyPath": "Sas Valley Road Hunza Gilgit Baltistan Pakistan",
        "adCount": 0,
        "aliases": [],
        "type": null,
        "hasBuilding": false,
        "trackID": "8091",
        "roles": null,
        "completionStatus": null,
        "hasChildren": false,
        "polygon": null,
        "objectID": "3950",
        "_highlightResult": {
            "name": {
                "value": "Sas Valley Road",
                "matchLevel": "none",
                "matchedWords": []
            }
        }
    },
    {
        "id": 3951,
        "name": "Shimshai Road",
        "name_l1": "شِمشائی روڈ",
        "externalID": "8092",
        "slug": "/Hunza_Shimshai_Road-8092",
        "slug_l1": "/Hunza_Shimshai_Road-8092",
        "_geoloc": {
            "lat": 36.496252,
            "lng": 74.91713
        },
        "geography": {
            "lat": 36.496252,
            "lng": 74.91713
        },
        "geo_point": [
            74.91713,
            36.496252
        ],
        "level": 3,
        "hierarchy": [
            {
                "id": 2,
                "level": 0,
                "externalID": "1521",
                "name": "Pakistan",
                "name_l1": "پاکستان",
                "slug": "/Pakistan-1521",
                "slug_l1": "/Pakistan-1521"
            },
            {
                "id": 8,
                "level": 1,
                "externalID": "1526",
                "name": "Gilgit Baltistan",
                "name_l1": "گلگت بلتستان",
                "slug": "/Gilgit_Baltistan-1526",
                "slug_l1": "/Gilgit_Baltistan-1526"
            },
            {
                "id": 79,
                "level": 2,
                "externalID": "1546",
                "name": "Hunza",
                "name_l1": "ہنزہ",
                "slug": "/Hunza-1546",
                "slug_l1": "/Hunza-1546"
            },
            {
                "id": 3951,
                "level": 3,
                "externalID": "8092",
                "name": "Shimshai Road",
                "name_l1": "شِمشائی روڈ",
                "slug": "/Hunza_Shimshai_Road-8092",
                "slug_l1": "/Hunza_Shimshai_Road-8092"
            }
        ],
        "hierarchyPath": "Shimshai Road Hunza Gilgit Baltistan Pakistan",
        "adCount": 0,
        "aliases": [],
        "type": null,
        "hasBuilding": false,
        "trackID": "8092",
        "roles": null,
        "completionStatus": null,
        "hasChildren": false,
        "polygon": null,
        "objectID": "3951",
        "_highlightResult": {
            "name": {
                "value": "Shimshai Road",
                "matchLevel": "none",
                "matchedWords": []
            }
        }
    },
    {
        "id": 18744,
        "name": "Sost Town",
        "name_l1": "سوسٹ ٹاؤن",
        "externalID": "19659",
        "slug": "/Hunza_Sost_Town-19659",
        "slug_l1": "/Hunza_Sost_Town-19659",
        "_geoloc": {
            "lat": 36.668574,
            "lng": 74.842991
        },
        "geography": {
            "lat": 36.668574,
            "lng": 74.842991
        },
        "geo_point": [
            74.842991,
            36.668574
        ],
        "level": 3,
        "hierarchy": [
            {
                "id": 2,
                "level": 0,
                "externalID": "1521",
                "name": "Pakistan",
                "name_l1": "پاکستان",
                "slug": "/Pakistan-1521",
                "slug_l1": "/Pakistan-1521"
            },
            {
                "id": 8,
                "level": 1,
                "externalID": "1526",
                "name": "Gilgit Baltistan",
                "name_l1": "گلگت بلتستان",
                "slug": "/Gilgit_Baltistan-1526",
                "slug_l1": "/Gilgit_Baltistan-1526"
            },
            {
                "id": 79,
                "level": 2,
                "externalID": "1546",
                "name": "Hunza",
                "name_l1": "ہنزہ",
                "slug": "/Hunza-1546",
                "slug_l1": "/Hunza-1546"
            },
            {
                "id": 18744,
                "level": 3,
                "externalID": "19659",
                "name": "Sost Town",
                "name_l1": "سوسٹ ٹاؤن",
                "slug": "/Hunza_Sost_Town-19659",
                "slug_l1": "/Hunza_Sost_Town-19659"
            }
        ],
        "hierarchyPath": "Sost Town Hunza Gilgit Baltistan Pakistan",
        "adCount": 0,
        "aliases": [],
        "type": null,
        "hasBuilding": false,
        "trackID": "19659",
        "roles": null,
        "completionStatus": null,
        "hasChildren": false,
        "polygon": null,
        "objectID": "18744",
        "_highlightResult": {
            "name": {
                "value": "Sost Town",
                "matchLevel": "none",
                "matchedWords": []
            }
        }
    },
    {
        "id": 3952,
        "name": "Sumayar Nagar",
        "name_l1": "سُمیار نگر",
        "externalID": "8093",
        "slug": "/Hunza_Sumayar_Nagar-8093",
        "slug_l1": "/Hunza_Sumayar_Nagar-8093",
        "_geoloc": {
            "lat": 36.302952,
            "lng": 74.652672
        },
        "geography": {
            "lat": 36.302952,
            "lng": 74.652672
        },
        "geo_point": [
            74.652672,
            36.302952
        ],
        "level": 3,
        "hierarchy": [
            {
                "id": 2,
                "level": 0,
                "externalID": "1521",
                "name": "Pakistan",
                "name_l1": "پاکستان",
                "slug": "/Pakistan-1521",
                "slug_l1": "/Pakistan-1521"
            },
            {
                "id": 8,
                "level": 1,
                "externalID": "1526",
                "name": "Gilgit Baltistan",
                "name_l1": "گلگت بلتستان",
                "slug": "/Gilgit_Baltistan-1526",
                "slug_l1": "/Gilgit_Baltistan-1526"
            },
            {
                "id": 79,
                "level": 2,
                "externalID": "1546",
                "name": "Hunza",
                "name_l1": "ہنزہ",
                "slug": "/Hunza-1546",
                "slug_l1": "/Hunza-1546"
            },
            {
                "id": 3952,
                "level": 3,
                "externalID": "8093",
                "name": "Sumayar Nagar",
                "name_l1": "سُمیار نگر",
                "slug": "/Hunza_Sumayar_Nagar-8093",
                "slug_l1": "/Hunza_Sumayar_Nagar-8093"
            }
        ],
        "hierarchyPath": "Sumayar Nagar Hunza Gilgit Baltistan Pakistan",
        "adCount": 0,
        "aliases": [],
        "type": null,
        "hasBuilding": false,
        "trackID": "8093",
        "roles": null,
        "completionStatus": null,
        "hasChildren": false,
        "polygon": null,
        "objectID": "3952",
        "_highlightResult": {
            "name": {
                "value": "Sumayar Nagar",
                "matchLevel": "none",
                "matchedWords": []
            }
        }
    },
    {
        "id": 3953,
        "name": "Toshat Phakkar Road",
        "name_l1": "توشت پکھر روڈ",
        "externalID": "8094",
        "slug": "/Hunza_Toshat_Phakkar_Road-8094",
        "slug_l1": "/Hunza_Toshat_Phakkar_Road-8094",
        "_geoloc": {
            "lat": 36.271473,
            "lng": 74.580002
        },
        "geography": {
            "lat": 36.271473,
            "lng": 74.580002
        },
        "geo_point": [
            74.580002,
            36.271473
        ],
        "level": 3,
        "hierarchy": [
            {
                "id": 2,
                "level": 0,
                "externalID": "1521",
                "name": "Pakistan",
                "name_l1": "پاکستان",
                "slug": "/Pakistan-1521",
                "slug_l1": "/Pakistan-1521"
            },
            {
                "id": 8,
                "level": 1,
                "externalID": "1526",
                "name": "Gilgit Baltistan",
                "name_l1": "گلگت بلتستان",
                "slug": "/Gilgit_Baltistan-1526",
                "slug_l1": "/Gilgit_Baltistan-1526"
            },
            {
                "id": 79,
                "level": 2,
                "externalID": "1546",
                "name": "Hunza",
                "name_l1": "ہنزہ",
                "slug": "/Hunza-1546",
                "slug_l1": "/Hunza-1546"
            },
            {
                "id": 3953,
                "level": 3,
                "externalID": "8094",
                "name": "Toshat Phakkar Road",
                "name_l1": "توشت پکھر روڈ",
                "slug": "/Hunza_Toshat_Phakkar_Road-8094",
                "slug_l1": "/Hunza_Toshat_Phakkar_Road-8094"
            }
        ],
        "hierarchyPath": "Toshat Phakkar Road Hunza Gilgit Baltistan Pakistan",
        "adCount": 0,
        "aliases": [],
        "type": null,
        "hasBuilding": false,
        "trackID": "8094",
        "roles": null,
        "completionStatus": null,
        "hasChildren": false,
        "polygon": null,
        "objectID": "3953",
        "_highlightResult": {
            "name": {
                "value": "Toshat Phakkar Road",
                "matchLevel": "none",
                "matchedWords": []
            }
        }
    }
]